simplicial_attention/__init__.py
simplicial_attention/nth_directional_attn.py
simplicial_attention/simplicial_attention.py
simplicial_attention/simplicial_mha.py
simplicial_attention/triton_two_simplicial_attention.py
simplicial_attention/two_simplicial_transformer.py
simplicial_attention-0.1.6.dist-info/METADATA
simplicial_attention-0.1.6.dist-info/WHEEL
simplicial_attention-0.1.6.dist-info/licenses/LICENSE
simplicial_attention-0.1.6.dist-info/RECORD
