Metadata-Version: 2.4
Name: simplicial-attention
Version: 0.1.6
Summary: (2) - Simplicial Attention
Project-URL: Homepage, https://pypi.org/project/simplicial-attention/
Project-URL: Repository, https://github.com/lucidrains/simplicial-attention
Author-email: Phil Wang <lucidrains@gmail.com>
License: MIT License
License-File: LICENSE
Keywords: artificial intelligence,attention mechanism,deep learning
Classifier: Development Status :: 4 - Beta
Classifier: Intended Audience :: Developers
Classifier: License :: OSI Approved :: MIT License
Classifier: Programming Language :: Python :: 3.9
Classifier: Topic :: Scientific/Engineering :: Artificial Intelligence
Requires-Python: >=3.9
Requires-Dist: einops>=0.8.1
Requires-Dist: hyper-connections>=0.2.1
Requires-Dist: opt-einsum
Requires-Dist: torch>=2.5
Requires-Dist: x-mlps-pytorch>=0.0.25
Provides-Extra: examples
Requires-Dist: tqdm; extra == 'examples'
Provides-Extra: test
Requires-Dist: pytest; extra == 'test'
